OrmKassDoug/Migration.py
OrmKassDoug/Model.py
OrmKassDoug/Querier.py
OrmKassDoug/__init__.py
OrmKassDoug-1.0.3.dist-info/LICENSE
OrmKassDoug-1.0.3.dist-info/METADATA
OrmKassDoug-1.0.3.dist-info/WHEEL
OrmKassDoug-1.0.3.dist-info/top_level.txt
OrmKassDoug-1.0.3.dist-info/RECORD
