Metadata-Version: 2.1
Name: OrmKassDoug
Version: 1.0.3
Summary: Gerenciar banco de dados
Home-page: https://github.com/seu-usuario/OrmKassDoug/
Author: Kássio Douglas
Author-email: kass.doug@gmail.com
License: MIT
Classifier: Development Status :: 3 - Alpha
Classifier: Intended Audience :: Developers
Classifier: License :: OSI Approved :: MIT License
Classifier: Programming Language :: Python :: 3
Classifier: Programming Language :: Python :: 3.6
Classifier: Programming Language :: Python :: 3.7
Classifier: Programming Language :: Python :: 3.8
Classifier: Programming Language :: Python :: 3.9
Classifier: Topic :: Software Development :: Libraries :: Python Modules
License-File: LICENSE
